gcspypi-1.0.1-nspkg.pth
ethronsoft/gcspypi/__init__.py
ethronsoft/gcspypi/__main__.py
ethronsoft/gcspypi/pb.py
ethronsoft/gcspypi/pm.py
ethronsoft/gcspypi/utils.py
gcspypi-1.0.1.dist-info/DESCRIPTION.rst
gcspypi-1.0.1.dist-info/METADATA
gcspypi-1.0.1.dist-info/RECORD
gcspypi-1.0.1.dist-info/WHEEL
gcspypi-1.0.1.dist-info/entry_points.txt
gcspypi-1.0.1.dist-info/metadata.json
gcspypi-1.0.1.dist-info/namespace_packages.txt
gcspypi-1.0.1.dist-info/top_level.txt
