Metadata-Version: 2.0
Name: gcspypi
Version: 1.0.1
Summary: Private packages repository backed by Google Cloud Storage
Home-page: https://github.com/ethronsoft/gcspypi
Author: Ethronsoft
Author-email: dev@ethronsoft.com
License: BSD 2-Clause License
Requires-Dist: google-cloud
